{
"autoplayBgm":true,"autoplayBgs":false,"battleback1Name":"","battleback2Name":"","bgm":{"name":"kitchen_beta","pan":0,"pitch":100,"volume":90},"bgs":{"name":"","pan":0,"pitch":100,"volume":90},"disableDashing":false,"displayName":"","encounterList":[],"encounterStep":30,"height":10,"note":"","parallaxLoopX":false,"parallaxLoopY":false,"parallaxName":"","parallaxShow":true,"parallaxSx":0,"parallaxSy":0,"scrollType":0,"specifyBattleback":false,"tilesetId":14,"width":15,
"data":[7640,8147,8146,8146,8146,8146,8146,8146,8146,8146,8146,8146,8146,8150,7632,7640,8153,8152,8152,8152,8152,8152,8152,8152,8152,8152,8152,8152,8156,7656,7640,4098,4084,4084,4084,4084,4100,3282,3268,3268,3268,3268,3268,3284,8151,7654,4080,4064,4064,4064,4064,4088,3264,3248,3248,3248,3248,3248,3272,8157,8151,4104,4092,4092,4092,4092,4102,3264,3248,3248,3248,3248,3248,3254,3281,8157,3282,3268,3268,3268,3268,3268,3249,3248,3248,3248,3248,3248,3272,7650,3281,3257,3248,3248,3248,3248,3248,3248,3248,3248,3248,3248,3248,3272,7632,7652,3264,3248,3248,3248,3248,3248,3248,3248,3248,3248,3248,3248,3272,7632,7640,3288,3276,3276,3276,3276,3276,3276,3276,3276,3276,3276,3276,3286,7632,7618,7636,7636,7636,7636,7636,7636,7636,7636,7636,7636,7636,7636,7636,7617,0,0,0,0,0,0,0,0,0,0,0,0,0,0,0,0,0,0,0,0,0,0,0,0,0,0,0,0,0,0,0,0,0,0,0,0,0,0,0,0,0,0,0,0,0,0,0,0,0,0,0,0,0,0,0,0,0,0,0,0,0,0,0,0,0,0,0,0,0,0,0,0,0,0,0,0,0,0,0,0,0,0,0,0,0,0,0,0,0,0,0,0,0,0,0,0,0,0,0,0,0,0,0,0,0,0,0,0,0,0,0,0,0,0,0,0,0,0,0,0,0,0,0,0,0,0,0,0,0,0,0,0,0,0,0,0,0,0,0,0,0,0,0,0,0,0,0,0,0,0,0,0,0,0,0,0,0,0,0,0,0,0,0,0,0,0,0,153,0,153,153,153,130,0,80,0,0,0,90,0,0,0,0,0,92,93,0,138,0,0,0,0,62,0,0,0,0,0,0,0,0,0,138,0,0,0,0,0,0,0,0,0,0,0,0,0,153,0,0,0,0,0,0,0,0,0,0,0,0,0,85,83,84,0,0,184,185,0,0,0,0,0,0,0,0,0,0,0,0,0,0,0,0,0,0,0,0,0,0,0,0,0,0,0,0,0,0,0,0,0,0,0,0,0,0,0,0,0,0,0,0,0,0,0,0,0,0,0,0,0,0,0,0,0,0,0,0,0,0,0,0,9,101,18,0,0,102,40,41,72,73,74,23,4,0,0,17,109,26,99,100,110,48,49,70,81,82,54,12,0,0,25,91,39,160,161,94,8,0,78,56,57,61,98,0,0,0,0,0,168,169,0,103,0,86,64,65,0,0,0,0,0,0,152,153,152,95,154,0,0,176,177,0,0,0,200,0,0,83,84,84,84,85,0,0,32,33,0,0,0,0,0,0,0,27,28,29,0,0,0,192,193,0,0,0,0,69,0,34,35,36,37,38,0,68,50,51,52,55,0,0,77,0,42,43,44,45,46,0,76,58,59,60,63,0,0,0,0,0,0,0,0,0,0,0,0,0,0,0,0,0,0,0,0,0,0,0,0,0,0,0,0,0,0,0,0,0,0,0,0,0,0,0,0,0,0,0,0,0,0,0,5,0,0,0,0,0,0,0,0,0,0,0,0,0,0,5,0,0,0,0,0,0,0,0,0,0,0,0,0,0,5,0,0,0,0,0,0,0,0,0,0,0,0,0,0,5,0,0,0,0,0,0,0,0,0,0,0,0,0,0,0,0,0,0,0,0,0,0,0,0,0,0,0,0,0,0,0,0,0,0,0,0,0,0,0,0,0,0,0,0,5,0,0,0,0,0,0,0,0,0,0,0,0,0,0,0,0,0,0,0,0,0,0,0,0,0,0,0,0,0,0,0,0,0,0,0,0,0,0,0,0,0,0,0,0,0,0,0,0,0,0,0,0,0,0,0,0,0,0,0,0,0,0,0,0,0,0,0,0,0,0,0,0,0,0,0,0,0,0,0,0,0,0,0,0,0,0,0,0,0,0,0,0,0,0,0,0,0,0,0,0,0,0,0,0,0,0,0,0,0,0,0,0,0,0,0,0,0,0,0,0,0,0,0,0,0,0,0,0,0,0,0,0,0,0,0,0,0,0,0,0,0,0,0,0,0,0,0,0,0,0,0,0,0,0,0,0,0,0,1,0,0,0,0,0,0,0,0,0,0,0,0,0,0,0,0,0,0,0],
"events":[
null,
{"id":1,"name":"AutoRunEvents","note":"","pages":[{"conditions":{"actorId":1,"actorValid":false,"itemId":1,"itemValid":false,"selfSwitchCh":"A","selfSwitchValid":false,"switch1Id":1,"switch1Valid":false,"switch2Id":1,"switch2Valid":false,"variableId":1,"variableValid":false,"variableValue":0},"directionFix":false,"image":{"characterIndex":0,"characterName":"","direction":2,"pattern":0,"tileId":0},"list":[{"code":222,"indent":0,"parameters":[]},{"code":101,"indent":0,"parameters":["",0,1,0]},{"code":401,"indent":0,"parameters":["\\n<Olivia>She\\..\\..\\.. \\.she picked me up.\\.\\.<br>She picked me up, \\.but she's not here."]},{"code":121,"indent":0,"parameters":[14,14,1]},{"code":123,"indent":0,"parameters":["A",0]},{"code":0,"indent":0,"parameters":[]}],"moveFrequency":3,"moveRoute":{"list":[{"code":0,"parameters":[]}],"repeat":true,"skippable":false,"wait":false},"moveSpeed":3,"moveType":0,"priorityType":0,"stepAnime":false,"through":false,"trigger":3,"walkAnime":true},{"conditions":{"actorId":1,"actorValid":false,"itemId":1,"itemValid":false,"selfSwitchCh":"A","selfSwitchValid":true,"switch1Id":1,"switch1Valid":false,"switch2Id":1,"switch2Valid":false,"variableId":1,"variableValid":false,"variableValue":0},"directionFix":false,"image":{"characterIndex":0,"characterName":"","direction":2,"pattern":0,"tileId":0},"list":[{"code":0,"indent":0,"parameters":[]}],"moveFrequency":3,"moveRoute":{"list":[{"code":0,"parameters":[]}],"repeat":true,"skippable":false,"wait":false},"moveSpeed":3,"moveType":0,"priorityType":0,"stepAnime":false,"through":false,"trigger":0,"walkAnime":true}],"x":0,"y":0},
{"id":2,"name":"EV002","note":"","pages":[{"conditions":{"actorId":1,"actorValid":false,"itemId":1,"itemValid":false,"selfSwitchCh":"A","selfSwitchValid":false,"switch1Id":1,"switch1Valid":false,"switch2Id":1,"switch2Valid":false,"variableId":1,"variableValid":false,"variableValue":0},"directionFix":false,"image":{"characterIndex":0,"characterName":"","direction":2,"pattern":0,"tileId":0},"list":[{"code":111,"indent":0,"parameters":[1,19,0,1,0]},{"code":111,"indent":1,"parameters":[1,20,0,2,0]},{"code":101,"indent":2,"parameters":["",0,1,0]},{"code":401,"indent":2,"parameters":["\\n<Olivia><br>\\..\\..\\.."]},{"code":101,"indent":2,"parameters":["",0,1,0]},{"code":401,"indent":2,"parameters":["\\n<Olivia><br>Here goes."]},{"code":242,"indent":2,"parameters":[2]},{"code":221,"indent":2,"parameters":[]},{"code":111,"indent":2,"parameters":[0,3,0]},{"code":121,"indent":3,"parameters":[3,3,1]},{"code":0,"indent":3,"parameters":[]},{"code":412,"indent":2,"parameters":[]},{"code":121,"indent":2,"parameters":[4,4,0]},{"code":121,"indent":2,"parameters":[8,8,0]},{"code":322,"indent":2,"parameters":[1,"",0,"Olivia_face_2",0,""]},{"code":201,"indent":2,"parameters":[0,7,0,3,0,0]},{"code":222,"indent":2,"parameters":[]},{"code":0,"indent":2,"parameters":[]},{"code":411,"indent":1,"parameters":[]},{"code":111,"indent":2,"parameters":[1,20,0,1,0]},{"code":101,"indent":3,"parameters":["",0,1,0]},{"code":401,"indent":3,"parameters":["\\n<Olivia>No, \\.no. \\.This feels wrong. \\.There's something missing, \\.I can \\fifeel \\frit."]},{"code":356,"indent":3,"parameters":["AltMovement move player left 1"]},{"code":0,"indent":3,"parameters":[]},{"code":411,"indent":2,"parameters":[]},{"code":101,"indent":3,"parameters":["",0,1,0]},{"code":401,"indent":3,"parameters":["\\n<Olivia>\\.I don't think it's a good idea to leave yet. \\.Somehow, \\.I just\\..\\..\\.. \\.don't feel ready."]},{"code":356,"indent":3,"parameters":["AltMovement move player left 1"]},{"code":0,"indent":3,"parameters":[]},{"code":412,"indent":2,"parameters":[]},{"code":0,"indent":2,"parameters":[]},{"code":412,"indent":1,"parameters":[]},{"code":0,"indent":1,"parameters":[]},{"code":411,"indent":0,"parameters":[]},{"code":101,"indent":1,"parameters":["",0,1,0]},{"code":401,"indent":1,"parameters":["\\n<Olivia>If I'm going to find Willow, \\.I'll want to take the car. \\.Where'd I leave my keys?"]},{"code":356,"indent":1,"parameters":["AltMovement move player left 1"]},{"code":0,"indent":1,"parameters":[]},{"code":412,"indent":0,"parameters":[]},{"code":0,"indent":0,"parameters":[]}],"moveFrequency":3,"moveRoute":{"list":[{"code":0,"parameters":[]}],"repeat":true,"skippable":false,"wait":false},"moveSpeed":3,"moveType":0,"priorityType":0,"stepAnime":false,"through":true,"trigger":1,"walkAnime":true}],"x":14,"y":4},
{"id":3,"name":"FindTile1","note":"","pages":[{"conditions":{"actorId":1,"actorValid":false,"itemId":6,"itemValid":false,"selfSwitchCh":"A","selfSwitchValid":false,"switch1Id":1,"switch1Valid":false,"switch2Id":1,"switch2Valid":false,"variableId":1,"variableValid":false,"variableValue":0},"directionFix":true,"image":{"tileId":0,"characterName":"","direction":8,"pattern":0,"characterIndex":6},"list":[{"code":101,"indent":0,"parameters":["",0,1,0]},{"code":401,"indent":0,"parameters":["\\n<Olivia><br>Half-eaten. \\.Willow doesn't leave food half-eaten."]},{"code":101,"indent":0,"parameters":["",0,1,0]},{"code":401,"indent":0,"parameters":["\\n<Olivia>\\..\\..\\..And she doesn't leave promises half-fulfilled. \\.She \\fipromised \\frto see me home. \\.She always does."]},{"code":101,"indent":0,"parameters":["",0,1,0]},{"code":401,"indent":0,"parameters":["\\n<Olivia><br>So where is she\\..\\..\\..\\.?"]},{"code":122,"indent":0,"parameters":[20,20,1,0,1]},{"code":123,"indent":0,"parameters":["A",0]},{"code":0,"indent":0,"parameters":[]}],"moveFrequency":3,"moveRoute":{"list":[{"code":0,"parameters":[]}],"repeat":true,"skippable":false,"wait":false},"moveSpeed":3,"moveType":0,"priorityType":1,"stepAnime":true,"through":false,"trigger":0,"walkAnime":false},{"conditions":{"actorId":1,"actorValid":false,"itemId":6,"itemValid":false,"selfSwitchCh":"A","selfSwitchValid":true,"switch1Id":1,"switch1Valid":false,"switch2Id":1,"switch2Valid":false,"variableId":1,"variableValid":false,"variableValue":0},"directionFix":false,"image":{"tileId":0,"characterName":"","direction":8,"pattern":0,"characterIndex":6},"list":[{"code":0,"indent":0,"parameters":[]}],"moveFrequency":3,"moveRoute":{"list":[{"code":0,"parameters":[]}],"repeat":true,"skippable":false,"wait":false},"moveSpeed":3,"moveType":0,"priorityType":1,"stepAnime":false,"through":false,"trigger":0,"walkAnime":true}],"x":4,"y":7},
{"id":4,"name":"Couch","note":"","pages":[{"conditions":{"actorId":1,"actorValid":false,"itemId":1,"itemValid":false,"selfSwitchCh":"A","selfSwitchValid":false,"switch1Id":14,"switch1Valid":false,"switch2Id":1,"switch2Valid":false,"variableId":19,"variableValid":false,"variableValue":1},"directionFix":true,"image":{"tileId":0,"characterName":"","direction":8,"pattern":0,"characterIndex":6},"list":[{"code":101,"indent":0,"parameters":["",0,1,0]},{"code":401,"indent":0,"parameters":["\\n<Olivia><br>H\\.-hold on. \\.These aren't mine."]},{"code":101,"indent":0,"parameters":["",0,1,0]},{"code":401,"indent":0,"parameters":["\\n<Olivia>These are Willow's keys\\..\\..\\.. \\.and they're in the \\ficouch \\frinstead of her key holder."]},{"code":101,"indent":0,"parameters":["",0,1,0]},{"code":401,"indent":0,"parameters":["\\n<Olivia>What's going on?<br>\\.\\.\\{Willow?\\}\\|\\.\\fiThis isn't funny!"]},{"code":122,"indent":0,"parameters":[19,19,0,0,1]},{"code":123,"indent":0,"parameters":["A",0]},{"code":0,"indent":0,"parameters":[]}],"moveFrequency":3,"moveRoute":{"list":[{"code":0,"parameters":[]}],"repeat":true,"skippable":false,"wait":false},"moveSpeed":3,"moveType":0,"priorityType":0,"stepAnime":true,"through":false,"trigger":0,"walkAnime":false},{"conditions":{"actorId":1,"actorValid":false,"itemId":1,"itemValid":false,"selfSwitchCh":"A","selfSwitchValid":true,"switch1Id":1,"switch1Valid":false,"switch2Id":1,"switch2Valid":false,"variableId":1,"variableValid":false,"variableValue":0},"directionFix":true,"image":{"tileId":0,"characterName":"","direction":8,"pattern":0,"characterIndex":6},"list":[{"code":0,"indent":0,"parameters":[]}],"moveFrequency":3,"moveRoute":{"list":[{"code":0,"parameters":[]}],"repeat":true,"skippable":false,"wait":false},"moveSpeed":3,"moveType":0,"priorityType":1,"stepAnime":true,"through":false,"trigger":0,"walkAnime":false}],"x":10,"y":3},
{"id":5,"name":"FindTile1","note":"","pages":[{"conditions":{"actorId":1,"actorValid":false,"itemId":6,"itemValid":false,"selfSwitchCh":"A","selfSwitchValid":false,"switch1Id":1,"switch1Valid":false,"switch2Id":1,"switch2Valid":false,"variableId":1,"variableValid":false,"variableValue":0},"directionFix":true,"image":{"tileId":1,"characterName":"","characterIndex":0,"direction":2,"pattern":0},"list":[{"code":101,"indent":0,"parameters":["",0,1,0]},{"code":401,"indent":0,"parameters":["\\n<Olivia><br>It's a note from her."]},{"code":101,"indent":0,"parameters":["",0,1,0]},{"code":401,"indent":0,"parameters":["\\n<Olivia>\\..\\..\\..\\.saying she'll pick me up at two unless Kyle calls earlier."]},{"code":101,"indent":0,"parameters":["",0,1,0]},{"code":401,"indent":0,"parameters":["\\n<Olivia>Do I really stay out that late?"]},{"code":401,"indent":0,"parameters":["<br>\\.\\.She\\..\\..\\.. really stays up that long for me, \\. doesn't she?"]},{"code":122,"indent":0,"parameters":[20,20,1,0,1]},{"code":123,"indent":0,"parameters":["A",0]},{"code":0,"indent":0,"parameters":[]}],"moveFrequency":3,"moveRoute":{"list":[{"code":0,"parameters":[]}],"repeat":true,"skippable":false,"wait":false},"moveSpeed":3,"moveType":0,"priorityType":0,"stepAnime":true,"through":false,"trigger":0,"walkAnime":false},{"conditions":{"actorId":1,"actorValid":false,"itemId":6,"itemValid":false,"selfSwitchCh":"A","selfSwitchValid":true,"switch1Id":1,"switch1Valid":false,"switch2Id":1,"switch2Valid":false,"variableId":1,"variableValid":false,"variableValue":0},"directionFix":false,"image":{"tileId":0,"characterName":"","direction":8,"pattern":0,"characterIndex":6},"list":[{"code":0,"indent":0,"parameters":[]}],"moveFrequency":3,"moveRoute":{"list":[{"code":0,"parameters":[]}],"repeat":true,"skippable":false,"wait":false},"moveSpeed":3,"moveType":0,"priorityType":2,"stepAnime":false,"through":false,"trigger":0,"walkAnime":true}],"x":3,"y":4},
null,
{"id":7,"name":"Couch","note":"","pages":[{"conditions":{"actorId":1,"actorValid":false,"itemId":1,"itemValid":false,"selfSwitchCh":"A","selfSwitchValid":false,"switch1Id":1,"switch1Valid":false,"switch2Id":1,"switch2Valid":false,"variableId":1,"variableValid":false,"variableValue":0},"directionFix":true,"image":{"tileId":0,"characterName":"","direction":8,"pattern":0,"characterIndex":6},"list":[{"code":101,"indent":0,"parameters":["",0,1,0]},{"code":401,"indent":0,"parameters":["\\n<Olivia>\\fiMy \\frkeys are probably under the rug again. \\.I'll have to pat around for this one."]},{"code":123,"indent":0,"parameters":["A",0]},{"code":0,"indent":0,"parameters":[]}],"moveFrequency":3,"moveRoute":{"list":[{"code":0,"parameters":[]}],"repeat":true,"skippable":false,"wait":false},"moveSpeed":3,"moveType":0,"priorityType":0,"stepAnime":true,"through":true,"trigger":0,"walkAnime":false},{"conditions":{"actorId":1,"actorValid":false,"itemId":1,"itemValid":false,"selfSwitchCh":"A","selfSwitchValid":true,"switch1Id":1,"switch1Valid":false,"switch2Id":1,"switch2Valid":false,"variableId":1,"variableValid":false,"variableValue":0},"directionFix":true,"image":{"tileId":0,"characterName":"","direction":8,"pattern":0,"characterIndex":6},"list":[{"code":0,"indent":0,"parameters":[]}],"moveFrequency":3,"moveRoute":{"list":[{"code":0,"parameters":[]}],"repeat":true,"skippable":false,"wait":false},"moveSpeed":3,"moveType":0,"priorityType":0,"stepAnime":true,"through":false,"trigger":0,"walkAnime":false}],"x":11,"y":6}
]
}